git2ignore/__init__.py
git2ignore/git2ignore.py
git2ignore/templates/.git
git2ignore/templates/.github/PULL_REQUEST_TEMPLATE.md
git2ignore/templates/AL.gitignore
git2ignore/templates/Actionscript.gitignore
git2ignore/templates/Ada.gitignore
git2ignore/templates/Agda.gitignore
git2ignore/templates/Android.gitignore
git2ignore/templates/AppEngine.gitignore
git2ignore/templates/AppceleratorTitanium.gitignore
git2ignore/templates/ArchLinuxPackages.gitignore
git2ignore/templates/Autotools.gitignore
git2ignore/templates/C++.gitignore
git2ignore/templates/C.gitignore
git2ignore/templates/CFWheels.gitignore
git2ignore/templates/CMake.gitignore
git2ignore/templates/CONTRIBUTING.md
git2ignore/templates/CUDA.gitignore
git2ignore/templates/CakePHP.gitignore
git2ignore/templates/ChefCookbook.gitignore
git2ignore/templates/CodeIgniter.gitignore
git2ignore/templates/CommonLisp.gitignore
git2ignore/templates/Composer.gitignore
git2ignore/templates/Concrete5.gitignore
git2ignore/templates/Coq.gitignore
git2ignore/templates/CraftCMS.gitignore
git2ignore/templates/D.gitignore
git2ignore/templates/DM.gitignore
git2ignore/templates/Dart.gitignore
git2ignore/templates/Delphi.gitignore
git2ignore/templates/Drupal.gitignore
git2ignore/templates/EPiServer.gitignore
git2ignore/templates/Eagle.gitignore
git2ignore/templates/Elisp.gitignore
git2ignore/templates/Elixir.gitignore
git2ignore/templates/Elm.gitignore
git2ignore/templates/Erlang.gitignore
git2ignore/templates/ExpressionEngine.gitignore
git2ignore/templates/ExtJs.gitignore
git2ignore/templates/Fancy.gitignore
git2ignore/templates/Finale.gitignore
git2ignore/templates/FlaxEngine.gitignore
git2ignore/templates/ForceDotCom.gitignore
git2ignore/templates/FuelPHP.gitignore
git2ignore/templates/GWT.gitignore
git2ignore/templates/Gcov.gitignore
git2ignore/templates/GitBook.gitignore
git2ignore/templates/Global/AL.gitignore
git2ignore/templates/Global/Anjuta.gitignore
git2ignore/templates/Global/Ansible.gitignore
git2ignore-0.1.4.dist-info/entry_points.txt
git2ignore-0.1.4.dist-info/LICENSE
git2ignore-0.1.4.dist-info/WHEEL
git2ignore-0.1.4.dist-info/METADATA
git2ignore-0.1.4.dist-info/RECORD
