Metadata-Version: 2.1
Name: git2ignore
Version: 0.1.4
Summary: python interface to generate .gitignore file.
License: MIT
Author: Kyoungseoun Chung
Author-email: kyoungseoun.chung@gmail.com
Requires-Python: >=3.10,<4.0
Classifier: License :: OSI Approved :: MIT License
Classifier: Programming Language :: Python :: 3
Classifier: Programming Language :: Python :: 3.10
